scripy_utils/__init__.py
scripy_utils/html_font_parse.py
scripy_utils/request_parse.py
scripy_utils/request_util.py
scripy_utils/selenium_util.py
scripy_utils/word_ans_util.py
scripy_utils/情感分析和词云绘制.py
scripy_utils/media/fake_useragent.json
scripy_utils/media/stopwords-master/README.md
scripy_utils/media/stopwords-master/baidu_stopwords.txt
scripy_utils/media/stopwords-master/cn_stopwords.txt
scripy_utils/media/stopwords-master/hit_stopwords.txt
scripy_utils/media/stopwords-master/scu_stopwords.txt
scripy_utils/media/wordcloud_imgs/2.jpg
scripy_utils/media/wordcloud_imgs/3.jpg
scripy_utils/media/wordcloud_imgs/3.png
scripy_utils/media/wordcloud_imgs/4.jpg
scripy_utils/media/wordcloud_imgs/4.png
scripy_utils/media/wordcloud_imgs/5.jpg
scripy_utils-0.0.3.dist-info/LICENSE
scripy_utils-0.0.3.dist-info/METADATA
scripy_utils-0.0.3.dist-info/WHEEL
scripy_utils-0.0.3.dist-info/top_level.txt
scripy_utils-0.0.3.dist-info/RECORD
