Metadata-Version: 2.1
Name: scripy-utils
Version: 0.0.3
Summary: Short description
Home-page: https://gitee.com/SkyOceanchen/scripy_utils.git
Author: SkyOceanChen
Author-email: skyoceanchen@foxmail.com
Maintainer: SkyOceanChen
Maintainer-email: skyoceanchen@foxmail.com
License: MIT
Keywords: basic_type,python
Classifier: Development Status :: 3 - Alpha
Classifier: Intended Audience :: Developers
Classifier: Operating System :: OS Independent
Classifier: Topic :: Software Development :: Build Tools
Classifier: License :: OSI Approved :: MIT License
Classifier: Programming Language :: Python :: 3.6
Classifier: Programming Language :: Python :: 3.8
Classifier: Programming Language :: Python :: 3.10
Requires-Python: ~=3.3
License-File: LICENSE
Requires-Dist: chardet
Requires-Dist: fontTools
Requires-Dist: selenium (==4.16.0)
Requires-Dist: requests (==2.31.0)
Requires-Dist: chardet (==3.0.4)
Requires-Dist: jieba (==0.42.1)
Requires-Dist: matplotlib (==3.7.0)
Requires-Dist: snownlp (==0.12.3)
Requires-Dist: textblob (==0.17.1)
Requires-Dist: wordcloud (==1.9.3)
